Metadata-Version: 1.1
Name: weakrefmethod
Version: 1.0.2
Summary: A WeakMethod class for storing bound methods using weak references.
Home-page: http://github.com/twang817/weakrefmethod
Author: Tommy Wang
Author-email: twang@august8.net
License: PSF
Download-URL: https://github.com/twang817/weakrefmethod/tarball/1.0.2
Keywords: weakref WeakMethod
Platform: UNKNOWN
Classifier: Development Status :: 3 - Alpha
Classifier: Environment :: Console
Classifier: Intended Audience :: Developers
Classifier: License :: OSI Approved :: Python Software Foundation License
Classifier: Programming Language :: Python
Classifier: Programming Language :: Python :: 2.6
Classifier: Programming Language :: Python :: 2.7
Classifier: Operating System :: OS Independent
Classifier: Topic :: Software Development :: Libraries
Classifier: Topic :: Software Development :: Libraries :: Python Modules
